aigve/__init__.py
aigve/main_aigve.py
aigve/configs/__init__.py
aigve/configs/blipsim.py
aigve/configs/clipsim.py
aigve/configs/cliptemp.py
aigve/configs/dsg.py
aigve/configs/fid.py
aigve/configs/fvd.py
aigve/configs/gstvqa.py
aigve/configs/gstvqa_crossdata.py
aigve/configs/is_score.py
aigve/configs/lightvqa_plus.py
aigve/configs/llm_score.py
aigve/configs/modular_bvqa.py
aigve/configs/pickscore.py
aigve/configs/simplevqa.py
aigve/configs/starvqa_plus.py
aigve/configs/tifa.py
aigve/configs/toy.py
aigve/configs/videophy.py
aigve/configs/videoscore.py
aigve/configs/viescore.py
aigve/core/__init__.py
aigve/core/loops.py
aigve/core/models.py
aigve/core/registry.py
aigve/datasets/__init__.py
aigve/datasets/blipsim_dataset.py
aigve/datasets/clipsim_dataset.py
aigve/datasets/cliptemp_dataset.py
aigve/datasets/dsg_dataset.py
aigve/datasets/fid_dataset.py
aigve/datasets/gstvqa_crossdata_dataset.py
aigve/datasets/gstvqa_dataset.py
aigve/datasets/kinetics_dataset.py
aigve/datasets/konvid_1k_dataset.py
aigve/datasets/lightvqa_plus_dataset.py
aigve/datasets/pickscore_dataset.py
aigve/datasets/simplevqa_dataset.py
aigve/datasets/tifa_dataset.py
aigve/datasets/toy_dataset.py
aigve/datasets/videophy_dataset.py
aigve/datasets/videoscore_dataset.py
aigve/datasets/vie_dataset.py
aigve/metrics/__init__.py
aigve/metrics/multi_aspect_metrics/__init__.py
aigve/metrics/multi_aspect_metrics/videophy/__init__.py
aigve/metrics/multi_aspect_metrics/videophy/videophy_metric.py
aigve/metrics/multi_aspect_metrics/videophy/vidophy_utils.py
aigve/metrics/multi_aspect_metrics/videophy/data_utils/__init__.py
aigve/metrics/multi_aspect_metrics/videophy/data_utils/randaugment.py
aigve/metrics/multi_aspect_metrics/videophy/data_utils/registry.py
aigve/metrics/multi_aspect_metrics/videophy/data_utils/xgpt3_dataset.py
aigve/metrics/multi_aspect_metrics/videophy/data_utils/processors/__init__.py
aigve/metrics/multi_aspect_metrics/videophy/data_utils/processors/builder.py
aigve-0.0.1.dist-info/licenses/LICENSE
aigve-0.0.1.dist-info/METADATA
aigve-0.0.1.dist-info/WHEEL
aigve-0.0.1.dist-info/top_level.txt
aigve-0.0.1.dist-info/RECORD
