Metadata-Version: 2.4
Name: aigve
Version: 0.0.1
Summary: A comprehensive and structured evaluation framework for assessing AI-generated video quality.
Home-page: https://www.aigve.org
Download-URL: https://github.com/ShaneXiangH/AIGVE_Tool
Author: Xinhao Xiang, Xiao Liu, Zizhong Li, Zhuosheng Liu
Author-email: xhxiang@ucdavis.edu
License: MIT License
Classifier: Programming Language :: Python :: 3
Classifier: License :: OSI Approved :: MIT License
Classifier: Operating System :: OS Independent
Requires-Python: >=3.10
License-File: LICENSE
Requires-Dist: torch==2.1.0
Requires-Dist: torchvision==0.16.0
Requires-Dist: torchaudio==0.12.1
Requires-Dist: numpy==1.23.5
Requires-Dist: scipy==1.14.1
Requires-Dist: pandas==2.2.3
Requires-Dist: pyyaml==6.0.2
Requires-Dist: tqdm==4.67.1
Requires-Dist: matplotlib==3.10.0
Requires-Dist: mmcv==2.2.0
Requires-Dist: mmdet==3.3.0
Requires-Dist: mmengine==0.10.6
Requires-Dist: transformers==4.46.3
Requires-Dist: sentencepiece==0.2.0
Requires-Dist: einops==0.8.1
Requires-Dist: openai==1.65.1
Requires-Dist: gdown==5.2.0
Requires-Dist: fvcore==0.1.5.post20221221
Requires-Dist: decord==0.6.0
Requires-Dist: pytorchvideo==0.1.5
Requires-Dist: clip==1.0
Requires-Dist: mkdocs-material==9.6.5
Requires-Dist: neoteroi-mkdocs==1.1.0
Requires-Dist: mkdocs-macros-plugin==1.3.7
Requires-Dist: mkdocs-jupyter==0.25.1
Requires-Dist: mkdocstrings==0.28.2
Requires-Dist: mkdocs-rss-plugin==1.17.1
Requires-Dist: mkdocs-exclude==1.0.2
Requires-Dist: mkdocstrings-python==1.16.2
Dynamic: author
Dynamic: author-email
Dynamic: classifier
Dynamic: description
Dynamic: description-content-type
Dynamic: download-url
Dynamic: home-page
Dynamic: license
Dynamic: license-file
Dynamic: requires-dist
Dynamic: requires-python
Dynamic: summary
